{
  "signal_portfolio": {
    "technical_signals": [
      {
        "name": "RSI",
        "correlation": 0.7,
        "weight": 0.05
      },
      {
        "name": "MACD",
        "correlation": 0.65,
        "weight": 0.05
      },
      {
        "name": "Bollinger",
        "correlation": 0.6,
        "weight": 0.05
      },
      {
        "name": "Volume",
        "correlation": 0.5,
        "weight": 0.05
      }
    ],
    "macro_signals": [
      {
        "name": "Inflation_Crisis",
        "correlation": 0.03,
        "weight": 0.15
      },
      {
        "name": "Regulatory_Flow",
        "correlation": 0.04,
        "weight": 0.05
      },
      {
        "name": "Global_Macro",
        "correlation": 0.02,
        "weight": 0.15
      }
    ],
    "adoption_signals": [
      {
        "name": "Chainalysis_Adoption",
        "correlation": 0.04,
        "weight": 0.15
      },
      {
        "name": "Regional_Growth",
        "correlation": 0.05,
        "weight": 0.1
      },
      {
        "name": "Institutional_Adoption",
        "correlation": 0.1,
        "weight": 0.1
      }
    ],
    "sentiment_signals": [
      {
        "name": "Social_Media",
        "correlation": 0.3,
        "weight": 0.05
      },
      {
        "name": "News_Sentiment",
        "correlation": 0.25,
        "weight": 0.05
      }
    ]
  },
  "metrics": {
    "category_correlations": {
      "technical_signals": 0.6125,
      "macro_signals": 0.030000000000000002,
      "adoption_signals": 0.06333333333333334,
      "sentiment_signals": 0.275
    },
    "category_weights": {
      "technical_signals": 0.2,
      "macro_signals": 0.35,
      "adoption_signals": 0.35,
      "sentiment_signals": 0.1
    },
    "weighted_correlation": 0.18266666666666667,
    "diversification_score": 0.8173333333333334,
    "diversification_rating": "EXCELLENT"
  },
  "timestamp": "2025-09-17T17:20:21.955451",
  "adoption_tracker_status": "enabled",
  "adoption_signal": "BUY"
}
