{
  "action_details": {
    "amount": 15000.0,
    "new_status": "PENDING_REVIEW",
    "review_queue": "senior_approvals",
    "state_key": "payment_443a8e8a-2df8-416d-a74b-973804ea170d"
  },
  "action_error": null,
  "action_id": "359af7ef-8ed3-4fd5-b155-a8d7d2b4ee90",
  "action_status": "success",
  "action_type": "state_transition",
  "decision_explanation": "Payment of $15000.00 exceeds threshold of $10000.00",
  "decision_hash": "3dc278d674dcef9530fc96e915850836d70ec643778c8ac373da3f0eec5e2765",
  "decision_id": "f5c55749-e249-4a05-9c2c-7e43ccd5edca",
  "decision_inputs": {
    "amount": 15000.0,
    "currency": "USD",
    "requestor_id": "r1",
    "threshold": 10000.0,
    "vendor_id": "v1"
  },
  "decision_outcome": "requires_review",
  "decision_rule": "payment_threshold_v1",
  "decision_rule_version": "1.0.0",
  "event_hash": "52faaad6e704e8965ee0918bf5e49a14997d74f97de5ce0548ec7dba5fc6e1b5",
  "event_id": "443a8e8a-2df8-416d-a74b-973804ea170d",
  "event_timestamp": "2025-12-19T11:59:53.358050+00:00",
  "event_type": "payment_request",
  "id": "9da871d2-6f28-4ded-b214-2b284bafeeb0",
  "proof_timestamp": "2025-12-19T11:59:53.358116+00:00",
  "version": "1.0.0"
}